text_engine/__init__.py
text_engine/dialog.py
text_engine/engine.py
text_engine/intents.py
text_engine/utils.py
text_engine/version.py
text_engine-0.0.1.dist-info/LICENSE
text_engine-0.0.1.dist-info/METADATA
text_engine-0.0.1.dist-info/WHEEL
text_engine-0.0.1.dist-info/top_level.txt
text_engine-0.0.1.dist-info/RECORD
