Metadata-Version: 2.1
Name: text-engine
Version: 0.0.1
Summary: interactive fiction engine
Home-page: https://github.com/TigreGotico/text_engine
Author: jarbasAI
Author-email: jarbasai@mailfence.com
License: Apache2.0
Platform: UNKNOWN
